postgres_connection_exporter/__init__.py
postgres_connection_exporter/__main__.py
postgres_connection_exporter/config.dist.yaml
postgres_connection_exporter-0.0.2.dist-info/METADATA
postgres_connection_exporter-0.0.2.dist-info/WHEEL
postgres_connection_exporter-0.0.2.dist-info/entry_points.txt
postgres_connection_exporter-0.0.2.dist-info/licenses/LICENSE
postgres_connection_exporter-0.0.2.dist-info/RECORD
