Metadata-Version: 2.3
Name: postgres-connection-exporter
Version: 0.0.2
Summary: A Prometheus exporter for PostgreSQL connection metrics
Project-URL: Homepage, https://git.private.coffee/kumi/postgres-connection-exporter
Project-URL: Bug Tracker, https://git.private.coffee/kumi/postgres-connection-exporter/issues
Project-URL: Source Code, https://git.private.coffee/kumi/postgres-connection-exporter
Author-email: Kumi Mitterer <postgres-connection-exporter@kumi.email>
License: Copyright (c) 2024 Kumi Mitterer <postgres-connection-exporter@kumi.email>
License-File: LICENSE
Classifier: License :: OSI Approved :: MIT License
Classifier: Operating System :: OS Independent
Classifier: Programming Language :: Python :: 3
Requires-Python: >=3.10
Requires-Dist: prometheus-client
Requires-Dist: psycopg2-binary
Requires-Dist: pyyaml
